__init__.py
get_secrets.py
getSecrets-1.1.dist-info/LICENSE
getSecrets-1.1.dist-info/METADATA
getSecrets-1.1.dist-info/WHEEL
getSecrets-1.1.dist-info/top_level.txt
getSecrets-1.1.dist-info/RECORD
