Metadata-Version: 2.1
Name: getSecrets
Version: 1.1
Summary: A library read secrets from hasicopr vault
Author-email: Xavier Mayeur <xavier@mayeur.be>
Project-URL: Homepage, https://github.com/xmayeur/getSecrets
Project-URL: Bug Tracker, https://github.com/xmayeur/getSecrets/issues
Classifier: Programming Language :: Python :: 3
Classifier: License :: OSI Approved :: MIT License
Classifier: Operating System :: OS Independent
Requires-Python: >=3.7
License-File: LICENSE
Requires-Dist: pyyaml
Requires-Dist: request
